interactions_unittest/__init__.py
interactions_unittest-1.0.3.dist-info/LICENSE
interactions_unittest-1.0.3.dist-info/METADATA
interactions_unittest-1.0.3.dist-info/WHEEL
interactions_unittest-1.0.3.dist-info/top_level.txt
interactions_unittest-1.0.3.dist-info/RECORD
